[
  {
    "id": "avg-sales",
    "label": "Średnia sprzedaż",
    "cells": [
      "-",
      "60,63",
      "62,80",
      "61,47",
      "62,05",
      "62,14",
      "61,17",
      "56,79",
      "52,09",
      "55,27",
      "57,51",
      "57,48",
      "55,95"
    ]
  },
  {
    "id": "customers-count",
    "label": "Ilość klientów",
    "cells": [
      "-",
      "3 334,00",
      "3 308,00",
      "3 361,00",
      "3 618,00",
      "3 527,00",
      "3 728,00",
      "3 516,00",
      "3 621,00",
      "3 526,00",
      "3 680,00",
      "3 855,00",
      "3 407,00"
    ]
  },
  {
    "id": "other-sales-qty",
    "label": "Sprzedaż pozostałe",
    "cells": [
      "-",
      "15 645,00",
      "16 116,00",
      "16 356,00",
      "17 265,00",
      "16 945,00",
      "17 550,00",
      "15 038,00",
      "14 268,00",
      "14 706,00",
      "15 604,00",
      "16 137,00",
      "13 857,00"
    ]
  },
  {
    "id": "customers-yoy",
    "label": "Klienci vs rok poprzedni %",
    "cells": [
      "-",
      "-",
      "-",
      "-",
      "-",
      "-",
      "-",
      "-",
      "-",
      "-",
      "-",
      "-",
      "-"
    ]
  },
  {
    "id": "sales-pizza-total",
    "label": "Pizza",
    "cells": [
      "-",
      "144 355,80",
      "147 587,30",
      "146 898,75",
      "164 619,83",
      "160 215,50",
      "160 652,87",
      "136 876,76",
      "128 875,42",
      "136 380,43",
      "150 867,57",
      "158 568,64",
      "136 841,89"
    ]
  },
  {
    "id": "pizzas-yoy",
    "label": "Pizze vs rok poprzedni %",
    "cells": [
      "-",
      "-",
      "-",
      "-",
      "-",
      "-",
      "-",
      "-",
      "-",
      "-",
      "-",
      "-",
      "-"
    ]
  },
  {
    "id": "drinks-sales",
    "label": "Napoje",
    "cells": [
      "-",
      "9 940,28",
      "9 525,80",
      "9 117,94",
      "9 803,40",
      "9 990,29",
      "10 026,99",
      "12 813,95",
      "14 319,36",
      "12 797,44",
      "13 432,47",
      "12 123,45",
      "10 825,67"
    ]
  },
  {
    "id": "drinks-pct",
    "label": "Sprzedaż napoje %",
    "cells": [
      "-",
      "4.9%",
      "4.6%",
      "4.4%",
      "4.4%",
      "4.6%",
      "4.4%",
      "6.4%",
      "7.6%",
      "6.6%",
      "6.3%",
      "5.5%",
      "5.7%"
    ]
  },
  {
    "id": "addons-sales",
    "label": "Sprzedaż dodatków",
    "cells": [
      "-",
      "17 213,70",
      "17 397,00",
      "17 303,13",
      "19 772,34",
      "19 005,55",
      "19 599,28",
      "17 100,99",
      "15 244,35",
      "16 817,75",
      "19 768,77",
      "24 493,23",
      "19 899,71"
    ]
  },
  {
    "id": "starters-sales",
    "label": "Startery",
    "cells": [
      "-",
      "5 743,58",
      "5 885,84",
      "6 972,42",
      "5 862,64",
      "7 086,51",
      "7 037,88",
      "7 257,40",
      "5 745,10",
      "5 548,76",
      "6 298,12",
      "6 459,76",
      "6 038,41"
    ]
  },
  {
    "id": "avg-bill",
    "label": "Średni rachunek",
    "cells": [
      "-",
      "60,63",
      "62,80",
      "61,47",
      "62,05",
      "62,14",
      "61,17",
      "56,79",
      "52,09",
      "55,27",
      "57,51",
      "57,48",
      "55,95"
    ]
  }
]